CeroCoinClient-2.0.1.html
MANIFEST.in
Makefile
README
setup.py
CeroCoinClient/CeroCoinClient.py
CeroCoinClient/__init__.py
CeroCoinClient.egg-info/PKG-INFO
CeroCoinClient.egg-info/SOURCES.txt
CeroCoinClient.egg-info/dependency_links.txt
CeroCoinClient.egg-info/top_level.txt
Examples/construct_and_run_client_node.py
PrimeGenerator/PrimeGenerator.py
PrimeGenerator/__init__.py
SHA256/SHA256.py
SHA256/__init__.py
TestCeroCoinClient/CeroCoinClient.py
TestCeroCoinClient/Test.py
TestCeroCoinClient/TestCeroCoinHashing.py