Metadata-Version: 1.1
Name: CeroCoinClient
Version: 2.0.1
Summary: A Python based educational platform for learning and teaching the basic concepts of crypto currencies
Home-page: https://engineering.purdue.edu/kak/distCeroCoin/CeroCoinClient-2.0.1.html
Author: Avinash Kak
Author-email: kak@purdue.edu
License: Python Software Foundation License
Download-URL: https://engineering.purdue.edu/kak/distCeroCoin/CeroCoinClient-2.0.1.tar.gz
Keywords: crypto currencies,hashing,public-key cryptography
Platform: All platforms
Classifier: Topic :: Scientific/Engineering :: Information Analysis
Classifier: Programming Language :: Python :: 2.7
Classifier: Programming Language :: Python :: 3.5
